setup.py
probability_ritvik/Binomialdistribution.py
probability_ritvik/Gaussiandistribution.py
probability_ritvik/Generaldistribution.py
probability_ritvik/__init__.py
probability_ritvik.egg-info/PKG-INFO
probability_ritvik.egg-info/SOURCES.txt
probability_ritvik.egg-info/dependency_links.txt
probability_ritvik.egg-info/not-zip-safe
probability_ritvik.egg-info/top_level.txt